instavm/__init__.py
instavm/exceptions.py
instavm/result.py
instavm/sandbox_client.py
instavm/integrations/__init__.py
instavm/integrations/azure_openai.py
instavm/integrations/langchain.py
instavm/integrations/llamaindex.py
instavm/integrations/ollama.py
instavm/integrations/openai.py
instavm-0.8.4.dist-info/METADATA
instavm-0.8.4.dist-info/WHEEL
instavm-0.8.4.dist-info/top_level.txt
instavm-0.8.4.dist-info/RECORD
