Metadata-Version: 2.4
Name: instavm
Version: 0.8.4
Summary: A simple API client for code execution
Home-page: http://instavm.io
Author: InstaVM Team
Author-email: hello@instavm.io
Classifier: Programming Language :: Python :: 3
Classifier: License :: OSI Approved :: MIT License
Classifier: Operating System :: OS Independent
Requires-Python: >=3.6
Requires-Dist: requests
Dynamic: author
Dynamic: author-email
Dynamic: classifier
Dynamic: description
Dynamic: description-content-type
Dynamic: home-page
Dynamic: requires-dist
Dynamic: requires-python
Dynamic: summary
